LICENSE
MANIFEST.in
README.md
pyproject.toml
setup.py
src/omsens/README.md
src/omsens/__init__.py
src/omsens/individual_sens_calculator.py
src/omsens/interactive_plot.py
src/omsens/multiparam_sweep.py
src/omsens/plot_predefined_heatmaps.py
src/omsens/predefined_plots_wp2.py
src/omsens/predefined_plots_wp3.py
src/omsens/setup.py
src/omsens/vectorial_analysis.py
src/omsens/world3_scenarios_sweeps_multiparam.py
src/omsens/world3_scenarios_sweeps_uniparam.py
src/omsens/analysis/__init__.py
src/omsens/analysis/indiv_sens.py
src/omsens/filesystem/__init__.py
src/omsens/filesystem/files_aux.py
src/omsens/fortran_interface/Curvif.for
src/omsens/fortran_interface/Curvif.o
src/omsens/fortran_interface/Curvif_simplified.f90
src/omsens/fortran_interface/Rut.for
src/omsens/fortran_interface/Rut.o
src/omsens/fortran_interface/Rutf.for
src/omsens/fortran_interface/Rutf.o
src/omsens/fortran_interface/curvif_simplified.cpython-310-x86_64-linux-gnu.so
src/omsens/fortran_interface/curvif_simplified.pyf
src/omsens/fortran_interface/readme.txt
src/omsens/misc/__init__.py
src/omsens/misc/csv_output_to_csv_matrix_converter.py
src/omsens/misc/parametersFromXMLToCSV.py
src/omsens/modelica_interface/__init__.py
src/omsens/modelica_interface/build_model.py
src/omsens/modelica_interface/compiled_model.py
src/omsens/modelica_interface/run_omc.py
src/omsens/mos_writer/__init__.py
src/omsens/mos_writer/calculate_sensitivities_mos_writer.py
src/omsens/mos_writer/formulas.py
src/omsens/mos_writer/mos_script_factory.py
src/omsens/mos_writer/parameter_sweep_settings.py
src/omsens/mos_writer/sweeping_mos_writer.py
src/omsens/plotting/__init__.py
src/omsens/plotting/plot_csv.py
src/omsens/plotting/plot_heatmap.py
src/omsens/plotting/plot_lines.py
src/omsens/plotting/plot_specs.py
src/omsens/plotting/plot_sweep.py
src/omsens/plotting/plot_vectorial.py
src/omsens/readme_writer/__init__.py
src/omsens/readme_writer/readme_writer.py
src/omsens/resource/BouncingBall.mo
src/omsens_linux_placiana.egg-info/PKG-INFO
src/omsens_linux_placiana.egg-info/SOURCES.txt
src/omsens_linux_placiana.egg-info/dependency_links.txt
src/omsens_linux_placiana.egg-info/not-zip-safe
src/omsens_linux_placiana.egg-info/requires.txt
src/omsens_linux_placiana.egg-info/top_level.txt