Metadata-Version: 2.1
Name: omsens-linux-placiana
Version: 1.0.8
Summary: OpenModelica sensitivity analysis and optimization module
Home-page: http://openmodelica.org/
Author: Rodrigo Castro
Author-email: rcastro@dc.uba.ar
Maintainer: Adeel Asghar
Maintainer-email: adeel.asghar@liu.se
License: BSD, OSMC-PL 1.2, GPL (user's choice)
Requires-Python: >=3.9
License-File: LICENSE
